gtests/MST.so
gtests/__init__.py
gtests/graphutilities.py
gtests/gtests.py
gtests/.ipynb_checkpoints/graphutilities-checkpoint.py
gtests/.ipynb_checkpoints/gtests-checkpoint.py
gtests-0.0.8.dist-info/METADATA
gtests-0.0.8.dist-info/WHEEL
gtests-0.0.8.dist-info/licenses/LICENSE
gtests-0.0.8.dist-info/RECORD
