Metadata-Version: 2.3
Name: gtests
Version: 0.0.8
Summary: Graph-Based Two Sample Test
Author-email: Alexander Wold <alexwold@iastate.edu>
License-File: LICENSE
Classifier: License :: OSI Approved :: GNU Affero General Public License v3
Classifier: Operating System :: OS Independent
Classifier: Programming Language :: Python :: 3
Requires-Python: >=3
